odoo8_addon_web_sheet_full_width-8.0.1.0.0-py2.7-nspkg.pth
odoo_addons/web_sheet_full_width/__openerp__.py
odoo_addons/web_sheet_full_width/__init__.py
odoo_addons/web_sheet_full_width/view/qweb.xml
odoo_addons/web_sheet_full_width/static/description/icon.png
odoo_addons/web_sheet_full_width/static/src/css/web_sheet_full_width.css
odoo8_addon_web_sheet_full_width-8.0.1.0.0.dist-info/top_level.txt
odoo8_addon_web_sheet_full_width-8.0.1.0.0.dist-info/WHEEL
odoo8_addon_web_sheet_full_width-8.0.1.0.0.dist-info/RECORD
odoo8_addon_web_sheet_full_width-8.0.1.0.0.dist-info/metadata.json
odoo8_addon_web_sheet_full_width-8.0.1.0.0.dist-info/DESCRIPTION.rst
odoo8_addon_web_sheet_full_width-8.0.1.0.0.dist-info/METADATA
odoo8_addon_web_sheet_full_width-8.0.1.0.0.dist-info/namespace_packages.txt
